{"name":"on","text":"on(event: 'change' | 'clearFilters' | 'clearSearch', callback: () => void): void","returnType":"void","args":[{"name":"event","type":"'change' | 'clearFilters' | 'clearSearch'","text":"event: 'change' | 'clearFilters' | 'clearSearch'"},{"name":"callback","type":"() => void","text":"callback: () => void"}],"ast":{"name":"on","kind":"Method","signatures":[{"return":{"type":{"text":"void","kind":"Intrinsic"}},"line":127,"parameters":[{"name":"event","type":{"text":"\"change\" | \"clearFilters\" | \"clearSearch\"","kind":"Union","elements":[{"text":"\"change\"","kind":"Literal"},{"text":"\"clearFilters\"","kind":"Literal"},{"text":"\"clearSearch\"","kind":"Literal"}]},"line":127},{"name":"callback","type":{"text":"() => void","kind":"Function","return":{"text":"void","kind":"Intrinsic"}},"line":127}]}]},"markdown":"\n<h2>Usage</h2>\n<h3><code>change</code> event</h3>\n<pre class=\"language-svelte\"><code class=\"language-svelte\"><span class=\"token tag\"><span class=\"token tag\"><span class=\"token punctuation\">&lt;</span>script</span><span class=\"token punctuation\">></span></span><span class=\"token script\"><span class=\"token language-javascript\">\n    <span class=\"token keyword\">let</span> element\n    table<span class=\"token punctuation\">.</span><span class=\"token function\">on</span><span class=\"token punctuation\">(</span><span class=\"token string\">'change'</span><span class=\"token punctuation\">,</span> <span class=\"token punctuation\">(</span><span class=\"token punctuation\">)</span> <span class=\"token operator\">=></span> element<span class=\"token punctuation\">.</span>scrollTop <span class=\"token operator\">=</span> <span class=\"token number\">0</span><span class=\"token punctuation\">)</span>\n</span></span><span class=\"token tag\"><span class=\"token tag\"><span class=\"token punctuation\">&lt;/</span>script</span><span class=\"token punctuation\">></span></span>\n\n<span class=\"token tag\"><span class=\"token tag\"><span class=\"token punctuation\">&lt;</span>div</span> <span class=\"token attr-name\"><span class=\"token namespace\">bind:</span>this=</span><span class=\"token language-javascript\"><span class=\"token punctuation\">&#123;</span>element<span class=\"token punctuation\">&#125;</span></span> <span class=\"token attr-name\"><span class=\"token namespace\">style:</span>height</span><span class=\"token attr-value\"><span class=\"token punctuation\">=</span><span class=\"token punctuation\">\"</span>600px<span class=\"token punctuation\">\"</span></span><span class=\"token punctuation\">></span></span>\n    <span class=\"token each\"><span class=\"token punctuation\">&#123;</span><span class=\"token keyword\">#each</span> <span class=\"token language-javascript\">table<span class=\"token punctuation\">.</span>rows </span><span class=\"token keyword\">as</span> <span class=\"token language-javascript\">row<span class=\"token punctuation\">&#125;</span></span></span>\n        [...]\n    <span class=\"token each\"><span class=\"token punctuation\">&#123;</span><span class=\"token keyword\">/each</span><span class=\"token punctuation\">&#125;</span></span>\n<span class=\"token tag\"><span class=\"token tag\"><span class=\"token punctuation\">&lt;/</span>div</span><span class=\"token punctuation\">></span></span></code></pre>\n<h3><code>clearFilters</code> event</h3>\n<pre class=\"language-svelte\"><code class=\"language-svelte\"><span class=\"token tag\"><span class=\"token tag\"><span class=\"token punctuation\">&lt;</span>script</span><span class=\"token punctuation\">></span></span><span class=\"token script\"><span class=\"token language-javascript\">\n    <span class=\"token keyword\">let</span> value <span class=\"token operator\">=</span> <span class=\"token function\">$state</span><span class=\"token punctuation\">(</span><span class=\"token string\">''</span><span class=\"token punctuation\">)</span>\n    table<span class=\"token punctuation\">.</span><span class=\"token function\">on</span><span class=\"token punctuation\">(</span><span class=\"token string\">'clearFilters'</span><span class=\"token punctuation\">,</span> <span class=\"token punctuation\">(</span><span class=\"token punctuation\">)</span> <span class=\"token operator\">=></span> value <span class=\"token operator\">=</span> <span class=\"token string\">''</span><span class=\"token punctuation\">)</span>\n</span></span><span class=\"token tag\"><span class=\"token tag\"><span class=\"token punctuation\">&lt;/</span>script</span><span class=\"token punctuation\">></span></span>\n\n<span class=\"token tag\"><span class=\"token tag\"><span class=\"token punctuation\">&lt;</span>input</span> <span class=\"token attr-name\">type</span><span class=\"token attr-value\"><span class=\"token punctuation\">=</span><span class=\"token punctuation\">\"</span>text<span class=\"token punctuation\">\"</span></span> <span class=\"token attr-name\">oninput=</span><span class=\"token language-javascript\"><span class=\"token punctuation\">&#123;</span><span class=\"token punctuation\">(</span><span class=\"token punctuation\">)</span> <span class=\"token operator\">=></span> table<span class=\"token punctuation\">.</span><span class=\"token function\">filter</span><span class=\"token punctuation\">(</span>value<span class=\"token punctuation\">,</span> <span class=\"token string\">'columnName'</span><span class=\"token punctuation\">)</span><span class=\"token punctuation\">&#125;</span></span><span class=\"token punctuation\">/></span></span></code></pre>\n<h3><code>clearSearch</code> event</h3>\n<pre class=\"language-svelte\"><code class=\"language-svelte\"><span class=\"token tag\"><span class=\"token tag\"><span class=\"token punctuation\">&lt;</span>script</span><span class=\"token punctuation\">></span></span><span class=\"token script\"><span class=\"token language-javascript\">\n    <span class=\"token keyword\">let</span> value <span class=\"token operator\">=</span> <span class=\"token function\">$state</span><span class=\"token punctuation\">(</span><span class=\"token string\">''</span><span class=\"token punctuation\">)</span>\n    table<span class=\"token punctuation\">.</span><span class=\"token function\">on</span><span class=\"token punctuation\">(</span><span class=\"token string\">'clearSearch'</span><span class=\"token punctuation\">,</span> <span class=\"token punctuation\">(</span><span class=\"token punctuation\">)</span> <span class=\"token operator\">=></span> value <span class=\"token operator\">=</span> <span class=\"token string\">''</span><span class=\"token punctuation\">)</span>\n</span></span><span class=\"token tag\"><span class=\"token tag\"><span class=\"token punctuation\">&lt;/</span>script</span><span class=\"token punctuation\">></span></span>\n\n<span class=\"token tag\"><span class=\"token tag\"><span class=\"token punctuation\">&lt;</span>input</span> <span class=\"token attr-name\">type</span><span class=\"token attr-value\"><span class=\"token punctuation\">=</span><span class=\"token punctuation\">\"</span>text<span class=\"token punctuation\">\"</span></span> <span class=\"token attr-name\">oninput=</span><span class=\"token language-javascript\"><span class=\"token punctuation\">&#123;</span><span class=\"token punctuation\">(</span><span class=\"token punctuation\">)</span> <span class=\"token operator\">=></span> table<span class=\"token punctuation\">.</span><span class=\"token function\">search</span><span class=\"token punctuation\">(</span>value<span class=\"token punctuation\">)</span><span class=\"token punctuation\">&#125;</span></span><span class=\"token punctuation\">/></span></span></code></pre>\n"}