{"name":"SearchType","text":"type SearchType = {\r\n    value: string,\r\n    scope?: Field<Row>[],\r\n    check?: Check\r\n}","ast":{"name":"SearchType","kind":"TypeAlias","line":28,"value":{"text":"{\r\n    value: string,\r\n    scope?: Field<Row>[],\r\n    check?: Check\r\n}","kind":"TypeLiteral","properties":[{"name":"value","kind":"Property","type":{"text":"string","kind":"Intrinsic"},"line":29},{"name":"scope","kind":"Property","type":{"text":"Field<Row>[] | undefined","kind":"Union","elements":[{"text":"Field<Row>[]","kind":"Array","elementType":{"text":"Field<Row>","kind":"Reference","source":{"line":18,"path":"..\\datatables\\src\\lib\\src\\client\\index.ts"},"typeArguments":[{"text":"Row","kind":"Reference","source":{"line":28,"path":"..\\datatables\\src\\lib\\src\\client\\index.ts"}}]}},{"text":"undefined","kind":"Intrinsic"}]},"line":30,"optional":true},{"name":"check","kind":"Property","type":{"text":"Check | undefined","kind":"Union","elements":[{"text":"Check","kind":"Reference","source":{"line":46,"path":"..\\datatables\\src\\lib\\src\\client\\index.ts"}},{"text":"undefined","kind":"Intrinsic"}]},"line":31,"optional":true}]},"typeParameters":[{"name":"Row"}]},"markdown":"<p style=\"color:var(--ternary)\">Documentation not found</p>"}